[{"chord_ID": "57", "chord_HTML": "V<sup>7</sup>", "probability": 1, "child_path": "17,27,b27,57"}, {"chord_ID": "57", "chord_HTML": "V<sup>7</sup>", "probability": 0.375, "child_path": "16,C16,27,57"}, {"chord_ID": "56/2", "chord_HTML": "V<sup>6</sup>/ii", "probability": 0.333, "child_path": "6,364,66,56/2"}, {"chord_ID": "2", "chord_HTML": "ii", "probability": 1, "child_path": "56,5,665,2"}, {"chord_ID": "5/6", "chord_HTML": "V/vi", "probability": 0.25, "child_path": "3,4,26,5/6"}, {"chord_ID": "57/6", "chord_HTML": "V<sup>7</sup>/vi", "probability": 0.667, "child_path": "36,443,37,57/6"}, {"chord_ID": "57", "chord_HTML": "V<sup>7</sup>", "probability": 0.429, "child_path": "56,6,27,57"}, {"chord_ID": "4", "chord_HTML": "IV", "probability": 0.292, "child_path": "1,56,6,4"}, {"chord_ID": "56", "chord_HTML": "V<sup>6</sup>", "probability": 0.053, "child_path": "b7,6,1,56"}, {"chord_ID": "2", "chord_HTML": "ii", "probability": 0.015, "child_path": "4,5,67,2"}, {"chord_ID": "3", "chord_HTML": "iii", "probability": 0.5, "child_path": "1,L242,5/5,3"}, {"chord_ID": "56", "chord_HTML": "V<sup>6</sup>", "probability": 0.25, "child_path": "6,2,464,56"}, {"chord_ID": "b7", "chord_HTML": "&#9837;VII", "probability": 0.005, "child_path": "1,16,4,b7"}, {"chord_ID": "4", "chord_HTML": "IV", "probability": 0.5, "child_path": "4,L27,47/4,4"}, {"chord_ID": "16", "chord_HTML": "I<sup>6</sup>", "probability": 1, "child_path": "1,564,Y3,16"}, {"chord_ID": "1", "chord_HTML": "I", "probability": 0.3, "child_path": "57,6,5,1"}, {"chord_ID": "4", "chord_HTML": "IV", "probability": 0.31, "child_path": "67,5,37,4"}, {"chord_ID": "6", "chord_HTML": "vi", "probability": 0.235, "child_path": "4,3,5/6,6"}, {"chord_ID": "164", "chord_HTML": "I<sup>6</sup><sub>4</sub>", "probability": 0.2, "child_path": "1,36,5,164"}, {"chord_ID": "1", "chord_HTML": "I", "probability": 0.02, "child_path": "47,5,27,1"}, {"chord_ID": "1", "chord_HTML": "I", "probability": 1, "child_path": "1,b3,b76,1"}, {"chord_ID": "265", "chord_HTML": "ii<sup>6</sup><sub>5</sub>", "probability": 0.13, "child_path": "1,6,16,265"}, {"chord_ID": "7/5", "chord_HTML": "vii&deg;/V", "probability": 0.154, "child_path": "642,L4,4,7/5"}, {"chord_ID": "464", "chord_HTML": "IV<sup>6</sup><sub>4</sub>", "probability": 0.893, "child_path": "6,464,6,464"}, {"chord_ID": "5", "chord_HTML": "V", "probability": 0.222, "child_path": "664,4,464,5"}, {"chord_ID": "1", "chord_HTML": "I", "probability": 0.176, "child_path": "6,5/5,4,1"}, {"chord_ID": "7/3", "chord_HTML": "vii&deg;/iii", "probability": 1, "child_path": "6,565/6,76/3,7/3"}, {"chord_ID": "4", "chord_HTML": "IV", "probability": 0.167, "child_path": "16,2,464,4"}, {"chord_ID": "5", "chord_HTML": "V", "probability": 0.5, "child_path": "57,365,6,5"}, {"chord_ID": "164", "chord_HTML": "I<sup>6</sup><sub>4</sub>", "probability": 0.386, "child_path": "564,5,1,164"}, {"chord_ID": "16", "chord_HTML": "I<sup>6</sup>", "probability": 1, "child_path": "5,464,57,16"}, {"chord_ID": "4", "chord_HTML": "IV", "probability": 0.158, "child_path": "4,542,3,4"}, {"chord_ID": "642", "chord_HTML": "vi<sup>4</sup><sub>2</sub>", "probability": 0.128, "child_path": "5/6,57/6,6,642"}, {"chord_ID": "16", "chord_HTML": "I<sup>6</sup>", "probability": 0.6, "child_path": "6,5/5,47,16"}, {"chord_ID": "3", "chord_HTML": "iii", "probability": 0.014, "child_path": "37,6,37,3"}, {"chord_ID": "b3", "chord_HTML": "&#9837;III", "probability": 0.024, "child_path": "b6,b7,1,b3"}, {"chord_ID": "6", "chord_HTML": "vi", "probability": 0.769, "child_path": "464,6,464,6"}, {"chord_ID": "564", "chord_HTML": "V<sup>6</sup><sub>4</sub>", "probability": 0.02, "child_path": "16,4,16,564"}, {"chord_ID": "5", "chord_HTML": "V", "probability": 0.382, "child_path": "16,1,4,5"}, {"chord_ID": "4", "chord_HTML": "IV", "probability": 0.3, "child_path": "67,17,37,4"}, {"chord_ID": "564", "chord_HTML": "V<sup>6</sup><sub>4</sub>", "probability": 0.024, "child_path": "2,1,4,564"}, {"chord_ID": "2", "chord_HTML": "ii", "probability": 0.103, "child_path": "6,365,47,2"}, {"chord_ID": "b77", "chord_HTML": "&#9837;VIIb7", "probability": 1, "child_path": "17,b77,17,b77"}, {"chord_ID": "57", "chord_HTML": "V<sup>7</sup>", "probability": 0.004, "child_path": "4,1,5,57"}, {"chord_ID": "5/6", "chord_HTML": "V/vi", "probability": 0.174, "child_path": "66,2,4,5/6"}, {"chord_ID": "4", "chord_HTML": "IV", "probability": 0.22, "child_path": "5,1,17,4"}, {"chord_ID": "D565", "chord_HTML": "v<sup>6</sup><sub>5</sub>", "probability": 1, "child_path": "665,D47,D57,D565"}, {"chord_ID": "2", "chord_HTML": "ii", "probability": 0.155, "child_path": "2,5,1,2"}, {"chord_ID": "36", "chord_HTML": "iii<sup>6</sup>", "probability": 1, "child_path": "5,36,67,36"}, {"chord_ID": "57", "chord_HTML": "V<sup>7</sup>", "probability": 0.038, "child_path": "3,1,3,57"}, {"chord_ID": "6", "chord_HTML": "vi", "probability": 1, "child_path": "4,464,3,6"}, {"chord_ID": "1", "chord_HTML": "I", "probability": 0.375, "child_path": "b7,4,67,1"}, {"chord_ID": "6", "chord_HTML": "vi", "probability": 1, "child_path": "5,46,36,6"}, {"chord_ID": "564", "chord_HTML": "V<sup>6</sup><sub>4</sub>", "probability": 1, "child_path": "46,66,4,564"}, {"chord_ID": "4", "chord_HTML": "IV", "probability": 0.4, "child_path": "16,543,1,4"}, {"chord_ID": "b7", "chord_HTML": "&#9837;VII", "probability": 0.011, "child_path": "4,5,2,b7"}, {"chord_ID": "57/4", "chord_HTML": "V<sup>7</sup>/IV", "probability": 0.1, "child_path": "1,364,1,57/4"}, {"chord_ID": "57/2", "chord_HTML": "V<sup>7</sup>/ii", "probability": 0.15, "child_path": "57/6,6,67,57/2"}, {"chord_ID": "b7", "chord_HTML": "&#9837;VII", "probability": 0.286, "child_path": "2,26,5,b7"}, {"chord_ID": "47", "chord_HTML": "IV<sup>7</sup>", "probability": 0.231, "child_path": "6,4,L4,47"}, {"chord_ID": "5", "chord_HTML": "V", "probability": 1, "child_path": "2,27,b77,5"}, {"chord_ID": "6", "chord_HTML": "vi", "probability": 0.6, "child_path": "7,6,77,6"}, {"chord_ID": "C5", "chord_HTML": "&#9837;V", "probability": 0.167, "child_path": "6,b6,5,C5"}, {"chord_ID": "C5", "chord_HTML": "&#9837;V", "probability": 0.003, "child_path": "3,6,4,C5"}, {"chord_ID": "46", "chord_HTML": "IV<sup>6</sup>", "probability": 0.5, "child_path": "46,56,6,46"}, {"chord_ID": "27", "chord_HTML": "ii<sup>7</sup>", "probability": 1, "child_path": "37,4,16,27"}, {"chord_ID": "6", "chord_HTML": "vi", "probability": 0.25, "child_path": "6,56/6,5/6,6"}, {"chord_ID": "57", "chord_HTML": "V<sup>7</sup>", "probability": 0.4, "child_path": "46,57,5,57"}, {"chord_ID": "5", "chord_HTML": "V", "probability": 0.145, "child_path": "5,27,4,5"}, {"chord_ID": "7/2", "chord_HTML": "vii&deg;/ii", "probability": 0.021, "child_path": "2,57,1,7/2"}, {"chord_ID": "57/2", "chord_HTML": "V<sup>7</sup>/ii", "probability": 0.24, "child_path": "4,542,37,57/2"}, {"chord_ID": "16", "chord_HTML": "I<sup>6</sup>", "probability": 0.14, "child_path": "47,6,1,16"}, {"chord_ID": "b7", "chord_HTML": "&#9837;VII", "probability": 1, "child_path": "1,b6,b3,b7"}, {"chord_ID": "3", "chord_HTML": "iii", "probability": 0.167, "child_path": "4,442,D442,3"}, {"chord_ID": "664", "chord_HTML": "vi<sup>6</sup><sub>4</sub>", "probability": 1, "child_path": "56,664,564,664"}, {"chord_ID": "2", "chord_HTML": "ii", "probability": 0.008, "child_path": "4,5,3,2"}, {"chord_ID": "5", "chord_HTML": "V", "probability": 1, "child_path": "564,16,164,5"}, {"chord_ID": "5", "chord_HTML": "V", "probability": 1, "child_path": "2,5/2,1,5"}, {"chord_ID": "57", "chord_HTML": "V<sup>7</sup>", "probability": 0.1, "child_path": "17,1,5,57"}, {"chord_ID": "6", "chord_HTML": "vi", "probability": 0.017, "child_path": "4,6,3,6"}, {"chord_ID": "665", "chord_HTML": "vi<sup>6</sup><sub>5</sub>", "probability": 0.009, "child_path": "b7,4,1,665"}, {"chord_ID": "1", "chord_HTML": "I", "probability": 0.114, "child_path": "27,5,6,1"}, {"chord_ID": "b3", "chord_HTML": "&#9837;III", "probability": 1, "child_path": "36,5,Y77,b3"}, {"chord_ID": "1", "chord_HTML": "I", "probability": 0.208, "child_path": "67,6,4,1"}, {"chord_ID": "5/6", "chord_HTML": "V/vi", "probability": 1, "child_path": "77,66,L27,5/6"}, {"chord_ID": "5/5", "chord_HTML": "V/V", "probability": 1, "child_path": "5,Y5,6,5/5"}, {"chord_ID": "543/4", "chord_HTML": "V<sup>4</sup><sub>3</sub>/IV", "probability": 0.043, "child_path": "5,564,1,543/4"}, {"chord_ID": "76", "chord_HTML": "vii&deg;<sup>6</sup>", "probability": 0.07, "child_path": "27,2,27,76"}, {"chord_ID": "17", "chord_HTML": "I<sup>7</sup>", "probability": 0.2, "child_path": "67,242,27,17"}, {"chord_ID": "47", "chord_HTML": "IV<sup>7</sup>", "probability": 0.097, "child_path": "77,5/6,6,47"}, {"chord_ID": "243", "chord_HTML": "ii<sup>4</sup><sub>3</sub>", "probability": 0.5, "child_path": "57,665,57,243"}, {"chord_ID": "142", "chord_HTML": "I<sup>4</sup><sub>2</sub>", "probability": 1, "child_path": "36,2,66,142"}, {"chord_ID": "1", "chord_HTML": "I", "probability": 1, "child_path": "46,1,464,1"}, {"chord_ID": "1", "chord_HTML": "I", "probability": 1, "child_path": "66,5,7,1"}, {"chord_ID": "b6", "chord_HTML": "&#9837;VI", "probability": 0.6, "child_path": "1,M142,6,b6"}, {"chord_ID": "37", "chord_HTML": "iii<sup>7</sup>", "probability": 0.115, "child_path": "6,5,47,37"}, {"chord_ID": "26", "chord_HTML": "ii<sup>6</sup>", "probability": 1, "child_path": "46,164,M5,26"}, {"chord_ID": "6", "chord_HTML": "vi", "probability": 0.273, "child_path": "67,47,67,6"}, {"chord_ID": "C57", "chord_HTML": "&#9837;V<sup>7</sup>", "probability": 0.097, "child_path": "47,57,1,C57"}, {"chord_ID": "47", "chord_HTML": "IV<sup>7</sup>", "probability": 0.5, "child_path": "242,17,67,47"}, {"chord_ID": "642", "chord_HTML": "vi<sup>4</sup><sub>2</sub>", "probability": 0.5, "child_path": "27,3,67,642"}, {"chord_ID": "5", "chord_HTML": "V", "probability": 0.288, "child_path": "4,2,6,5"}, {"chord_ID": "46", "chord_HTML": "IV<sup>6</sup>", "probability": 1, "child_path": "364,46,164,46"}, {"chord_ID": "b7", "chord_HTML": "&#9837;VII", "probability": 1, "child_path": "57/2,27,242,b7"}, {"chord_ID": "4", "chord_HTML": "IV", "probability": 0.667, "child_path": "5/6,6,37,4"}, {"chord_ID": "5", "chord_HTML": "V", "probability": 0.114, "child_path": "1,47,6,5"}, {"chord_ID": "1", "chord_HTML": "I", "probability": 0.273, "child_path": "3,1,5/5,1"}, {"chord_ID": "Y4", "chord_HTML": "iv", "probability": 1, "child_path": "2,b5,Y1,Y4"}, {"chord_ID": "2", "chord_HTML": "ii", "probability": 0.077, "child_path": "1,37,6,2"}, {"chord_ID": "4", "chord_HTML": "IV", "probability": 0.79, "child_path": "1,2,16,4"}, {"chord_ID": "1", "chord_HTML": "I", "probability": 1, "child_path": "5/6,2,57,1"}, {"chord_ID": "17", "chord_HTML": "I<sup>7</sup>", "probability": 1, "child_path": "564,364,464,17"}, {"chord_ID": "66", "chord_HTML": "vi<sup>6</sup>", "probability": 0.769, "child_path": "564,664,16,66"}, {"chord_ID": "37", "chord_HTML": "iii<sup>7</sup>", "probability": 0.002, "child_path": "5,6,1,37"}, {"chord_ID": "4", "chord_HTML": "IV", "probability": 0.176, "child_path": "5,6,264,4"}, {"chord_ID": "3", "chord_HTML": "iii", "probability": 0.333, "child_path": "b4,b464,b4,3"}, {"chord_ID": "2", "chord_HTML": "ii", "probability": 1, "child_path": "56/6,164,77/5,2"}, {"chord_ID": "57", "chord_HTML": "V<sup>7</sup>", "probability": 1, "child_path": "27,66,565,57"}, {"chord_ID": "b7", "chord_HTML": "&#9837;VII", "probability": 0.333, "child_path": "6,b7,46,b7"}, {"chord_ID": "66", "chord_HTML": "vi<sup>6</sup>", "probability": 0.4, "child_path": "37,365,343,66"}, {"chord_ID": "6", "chord_HTML": "vi", "probability": 0.226, "child_path": "6,1,364,6"}, {"chord_ID": "2", "chord_HTML": "ii", "probability": 1, "child_path": "7/6,6,66,2"}, {"chord_ID": "17", "chord_HTML": "I<sup>7</sup>", "probability": 1, "child_path": "b7,67,6,17"}, {"chord_ID": "2", "chord_HTML": "ii", "probability": 0.009, "child_path": "1,b7,4,2"}, {"chord_ID": "b77", "chord_HTML": "&#9837;VIIb7", "probability": 0.086, "child_path": "57/2,57/5,57,b77"}, {"chord_ID": "5", "chord_HTML": "V", "probability": 1, "child_path": "1,b3,D4,5"}, {"chord_ID": "57", "chord_HTML": "V<sup>7</sup>", "probability": 1, "child_path": "1,b7,b67,57"}, {"chord_ID": "b7", "chord_HTML": "&#9837;VII", "probability": 1, "child_path": "2,7,17,b7"}, {"chord_ID": "5", "chord_HTML": "V", "probability": 1, "child_path": "5,37,542,5"}, {"chord_ID": "b7", "chord_HTML": "&#9837;VII", "probability": 1, "child_path": "2,b7,56,b7"}, {"chord_ID": "5/6", "chord_HTML": "V/vi", "probability": 0.078, "child_path": "1,5/6,6,5/6"}, {"chord_ID": "M4", "chord_HTML": "IV", "probability": 0.027, "child_path": "1,6,b7,M4"}, {"chord_ID": "67", "chord_HTML": "vi<sup>7</sup>", "probability": 1, "child_path": "56,M56,2,67"}, {"chord_ID": "2", "chord_HTML": "ii", "probability": 0.5, "child_path": "242,264,242,2"}, {"chord_ID": "5/5", "chord_HTML": "V/V", "probability": 0.008, "child_path": "6,5,6,5/5"}, {"chord_ID": "1", "chord_HTML": "I", "probability": 1, "child_path": "7/6,6,364,1"}, {"chord_ID": "1", "chord_HTML": "I", "probability": 0.111, "child_path": "67,27,4,1"}, {"chord_ID": "6", "chord_HTML": "vi", "probability": 1, "child_path": "17,5/6,56/6,6"}, {"chord_ID": "5/6", "chord_HTML": "V/vi", "probability": 0.039, "child_path": "5,4,2,5/6"}, {"chord_ID": "17", "chord_HTML": "I<sup>7</sup>", "probability": 0.049, "child_path": "6,5/5,5,17"}, {"chord_ID": "27", "chord_HTML": "ii<sup>7</sup>", "probability": 0.5, "child_path": "5,27,2,27"}, {"chord_ID": "164", "chord_HTML": "I<sup>6</sup><sub>4</sub>", "probability": 0.5, "child_path": "642,164,57,164"}, {"chord_ID": "5", "chord_HTML": "V", "probability": 0.389, "child_path": "66,16,4,5"}, {"chord_ID": "57/2", "chord_HTML": "V<sup>7</sup>/ii", "probability": 0.021, "child_path": "4,5,16,57/2"}, {"chord_ID": "165", "chord_HTML": "I<sup>6</sup><sub>5</sub>", "probability": 0.018, "child_path": "6,3,4,165"}, {"chord_ID": "27", "chord_HTML": "ii<sup>7</sup>", "probability": 0.375, "child_path": "5,56/6,5/6,27"}, {"chord_ID": "2", "chord_HTML": "ii", "probability": 0.75, "child_path": "2,27,76,2"}, {"chord_ID": "164", "chord_HTML": "I<sup>6</sup><sub>4</sub>", "probability": 0.261, "child_path": "542,3,6,164"}, {"chord_ID": "5/5", "chord_HTML": "V/V", "probability": 0.006, "child_path": "5/6,6,4,5/5"}, {"chord_ID": "2", "chord_HTML": "ii", "probability": 1, "child_path": "5/5,56,M56,2"}, {"chord_ID": "6", "chord_HTML": "vi", "probability": 1, "child_path": "67,164,36,6"}, {"chord_ID": "37", "chord_HTML": "iii<sup>7</sup>", "probability": 0.003, "child_path": "1,6,5,37"}, {"chord_ID": "37", "chord_HTML": "iii<sup>7</sup>", "probability": 0.121, "child_path": "67,47,27,37"}, {"chord_ID": "4", "chord_HTML": "IV", "probability": 0.75, "child_path": "b6,b3,b7,4"}, {"chord_ID": "4", "chord_HTML": "IV", "probability": 1, "child_path": "b6,C57,M4,4"}, {"chord_ID": "1", "chord_HTML": "I", "probability": 1, "child_path": "5,b7,D3,1"}, {"chord_ID": "6", "chord_HTML": "vi", "probability": 1, "child_path": "27,4,57/6,6"}, {"chord_ID": "3", "chord_HTML": "iii", "probability": 1, "child_path": "3,b3,1,3"}, {"chord_ID": "5", "chord_HTML": "V", "probability": 0.053, "child_path": "1,164,6,5"}, {"chord_ID": "464", "chord_HTML": "IV<sup>6</sup><sub>4</sub>", "probability": 0.048, "child_path": "164,1,4,464"}, {"chord_ID": "57/6", "chord_HTML": "V<sup>7</sup>/vi", "probability": 1, "child_path": "6,5/3,76,57/6"}, {"chord_ID": "1", "chord_HTML": "I", "probability": 0.667, "child_path": "264,5/2,2,1"}, {"chord_ID": "4", "chord_HTML": "IV", "probability": 0.182, "child_path": "4,1,56,4"}, {"chord_ID": "5/6", "chord_HTML": "V/vi", "probability": 0.2, "child_path": "5,4,5/5,5/6"}, {"chord_ID": "b46", "chord_HTML": "iv<sup>6</sup>", "probability": 0.039, "child_path": "4,1,164,b46"}, {"chord_ID": "16", "chord_HTML": "I<sup>6</sup>", "probability": 0.6, "child_path": "57/5,1,4,16"}, {"chord_ID": "26", "chord_HTML": "ii<sup>6</sup>", "probability": 0.001, "child_path": "5,1,4,26"}, {"chord_ID": "542", "chord_HTML": "V<sup>4</sup><sub>2</sub>", "probability": 0.25, "child_path": "1,5,564,542"}, {"chord_ID": "47", "chord_HTML": "IV<sup>7</sup>", "probability": 1, "child_path": "57/6,543/6,6,47"}, {"chord_ID": "164", "chord_HTML": "I<sup>6</sup><sub>4</sub>", "probability": 0.176, "child_path": "1,4,564,164"}, {"chord_ID": "5/6", "chord_HTML": "V/vi", "probability": 0.05, "child_path": "6,47,1,5/6"}, {"chord_ID": "464", "chord_HTML": "IV<sup>6</sup><sub>4</sub>", "probability": 0.002, "child_path": "4,1,4,464"}, {"chord_ID": "6", "chord_HTML": "vi", "probability": 1, "child_path": "6,D6,66,6"}, {"chord_ID": "2", "chord_HTML": "ii", "probability": 1, "child_path": "464,442,4,2"}, {"chord_ID": "4", "chord_HTML": "IV", "probability": 1, "child_path": "364,464,17,4"}, {"chord_ID": "b67", "chord_HTML": "&#9837;VI<sup>7</sup>", "probability": 0.025, "child_path": "27,57,1,b67"}, {"chord_ID": "57", "chord_HTML": "V<sup>7</sup>", "probability": 0.043, "child_path": "364,6,5,57"}, {"chord_ID": "1", "chord_HTML": "I", "probability": 0.6, "child_path": "464,M17,464,1"}, {"chord_ID": "2", "chord_HTML": "ii", "probability": 0.25, "child_path": "6,464,364,2"}, {"chord_ID": "67", "chord_HTML": "vi<sup>7</sup>", "probability": 0.5, "child_path": "4,5,36,67"}, {"chord_ID": "5", "chord_HTML": "V", "probability": 1, "child_path": "46,36,6,5"}, {"chord_ID": "5/6", "chord_HTML": "V/vi", "probability": 0.208, "child_path": "6,5,5/5,5/6"}, {"chord_ID": "6", "chord_HTML": "vi", "probability": 0.174, "child_path": "5,4,1,6"}, {"chord_ID": "56/6", "chord_HTML": "V<sup>6</sup>/vi", "probability": 0.115, "child_path": "37,27,57,56/6"}, {"chord_ID": "b77", "chord_HTML": "&#9837;VIIb7", "probability": 0.176, "child_path": "2,57/2,2,b77"}, {"chord_ID": "57", "chord_HTML": "V<sup>7</sup>", "probability": 0.038, "child_path": "46,164,4,57"}, {"chord_ID": "4", "chord_HTML": "IV", "probability": 0.714, "child_path": "1,5/5,b3,4"}, {"chord_ID": "6", "chord_HTML": "vi", "probability": 1, "child_path": "b4,6,D3,6"}, {"chord_ID": "342", "chord_HTML": "iii<sup>4</sup><sub>2</sub>", "probability": 0.002, "child_path": "4,5,2,342"}, {"chord_ID": "6", "chord_HTML": "vi", "probability": 1, "child_path": "1,164,36,6"}, {"chord_ID": "47", "chord_HTML": "IV<sup>7</sup>", "probability": 0.333, "child_path": "2,1,67,47"}, {"chord_ID": "5", "chord_HTML": "V", "probability": 1, "child_path": "26,16,26,5"}, {"chord_ID": "57", "chord_HTML": "V<sup>7</sup>", "probability": 1, "child_path": "542,16,243,57"}, {"chord_ID": "6", "chord_HTML": "vi", "probability": 1, "child_path": "265,1,5/6,6"}, {"chord_ID": "76/5", "chord_HTML": "vii&deg;<sup>6</sup>/V", "probability": 1, "child_path": "7,16,5,76/5"}, {"chord_ID": "1", "chord_HTML": "I", "probability": 0.094, "child_path": "6,36,4,1"}, {"chord_ID": "5/5", "chord_HTML": "V/V", "probability": 0.469, "child_path": "5/5,6,5,5/5"}, {"chord_ID": "264", "chord_HTML": "ii<sup>6</sup><sub>4</sub>", "probability": 0.222, "child_path": "6,D6,6,264"}, {"chord_ID": "37", "chord_HTML": "iii<sup>7</sup>", "probability": 0.149, "child_path": "5,47,1,37"}, {"chord_ID": "3", "chord_HTML": "iii", "probability": 1, "child_path": "364,3,36,3"}, {"chord_ID": "1", "chord_HTML": "I", "probability": 0.667, "child_path": "6,46,2,1"}, {"chord_ID": "5", "chord_HTML": "V", "probability": 1, "child_path": "5/2,27,26,5"}, {"chord_ID": "56", "chord_HTML": "V<sup>6</sup>", "probability": 0.068, "child_path": "4,56,1,56"}, {"chord_ID": "664", "chord_HTML": "vi<sup>6</sup><sub>4</sub>", "probability": 0.5, "child_path": "5/6,27,7/3,664"}, {"chord_ID": "5", "chord_HTML": "V", "probability": 1, "child_path": "5,265,665,5"}, {"chord_ID": "4", "chord_HTML": "IV", "probability": 1, "child_path": "1,66,57/4,4"}, {"chord_ID": "1", "chord_HTML": "I", "probability": 0.308, "child_path": "1,b7,2,1"}, {"chord_ID": "3", "chord_HTML": "iii", "probability": 1, "child_path": "37,3,5/6,3"}, {"chord_ID": "6", "chord_HTML": "vi", "probability": 0.649, "child_path": "1,5,5/6,6"}, {"chord_ID": "37", "chord_HTML": "iii<sup>7</sup>", "probability": 1, "child_path": "66,67,1,37"}, {"chord_ID": "16", "chord_HTML": "I<sup>6</sup>", "probability": 0.1, "child_path": "2,1,4,16"}, {"chord_ID": "47", "chord_HTML": "IV<sup>7</sup>", "probability": 0.013, "child_path": "1,5,6,47"}, {"chord_ID": "643", "chord_HTML": "vi<sup>4</sup><sub>3</sub>", "probability": 1, "child_path": "67,L77,47,643"}, {"chord_ID": "4", "chord_HTML": "IV", "probability": 1, "child_path": "56/6,642,L4,4"}, {"chord_ID": "17", "chord_HTML": "I<sup>7</sup>", "probability": 1, "child_path": "5,565/6,47,17"}, {"chord_ID": "4", "chord_HTML": "IV", "probability": 1, "child_path": "4,3,47/4,4"}, {"chord_ID": "1", "chord_HTML": "I", "probability": 1, "child_path": "542,543,57,1"}, {"chord_ID": "16", "chord_HTML": "I<sup>6</sup>", "probability": 0.006, "child_path": "1,464,1,16"}, {"chord_ID": "564", "chord_HTML": "V<sup>6</sup><sub>4</sub>", "probability": 0.111, "child_path": "664,6,5,564"}, {"chord_ID": "5/6", "chord_HTML": "V/vi", "probability": 0.16, "child_path": "6,4,2,5/6"}, {"chord_ID": "364", "chord_HTML": "iii<sup>6</sup><sub>4</sub>", "probability": 1, "child_path": "27,77,1,364"}, {"chord_ID": "M57", "chord_HTML": "v<sup>7</sup>", "probability": 0.024, "child_path": "27,57/6,67,M57"}, {"chord_ID": "1", "chord_HTML": "I", "probability": 0.429, "child_path": "5,57/6,4,1"}, {"chord_ID": "16", "chord_HTML": "I<sup>6</sup>", "probability": 0.071, "child_path": "56,1,27,16"}, {"chord_ID": "b4", "chord_HTML": "iv", "probability": 0.091, "child_path": "1,57,4,b4"}, {"chord_ID": "56", "chord_HTML": "V<sup>6</sup>", "probability": 0.022, "child_path": "56,1,2,56"}, {"chord_ID": "56", "chord_HTML": "V<sup>6</sup>", "probability": 1, "child_path": "56,66,46,56"}, {"chord_ID": "b6", "chord_HTML": "&#9837;VI", "probability": 0.143, "child_path": "6,5,57,b6"}, {"chord_ID": "6", "chord_HTML": "vi", "probability": 0.6, "child_path": "242,56,1,6"}, {"chord_ID": "27", "chord_HTML": "ii<sup>7</sup>", "probability": 1, "child_path": "264,16,264,27"}, {"chord_ID": "4", "chord_HTML": "IV", "probability": 0.375, "child_path": "27,3,6,4"}, {"chord_ID": "1", "chord_HTML": "I", "probability": 0.5, "child_path": "57,6,7/5,1"}, {"chord_ID": "56", "chord_HTML": "V<sup>6</sup>", "probability": 0.012, "child_path": "47,37,6,56"}, {"chord_ID": "264", "chord_HTML": "ii<sup>6</sup><sub>4</sub>", "probability": 1, "child_path": "57/6,6,M67,264"}, {"chord_ID": "565/5", "chord_HTML": "V<sup>6</sup><sub>5</sub>/V", "probability": 0.028, "child_path": "1,57/4,4,565/5"}, {"chord_ID": "b3", "chord_HTML": "&#9837;III", "probability": 1, "child_path": "1,b4,b7,b3"}, {"chord_ID": "16", "chord_HTML": "I<sup>6</sup>", "probability": 0.066, "child_path": "6,66,4,16"}, {"chord_ID": "17", "chord_HTML": "I<sup>7</sup>", "probability": 0.001, "child_path": "6,4,5,17"}, {"chord_ID": "5/6", "chord_HTML": "V/vi", "probability": 0.263, "child_path": "6,47,365,5/6"}, {"chord_ID": "5/5", "chord_HTML": "V/V", "probability": 0.006, "child_path": "1,6,1,5/5"}, {"chord_ID": "26", "chord_HTML": "ii<sup>6</sup>", "probability": 0.6, "child_path": "6,26,3,26"}, {"chord_ID": "7/3", "chord_HTML": "vii&deg;/iii", "probability": 0.5, "child_path": "36,5/6,6,7/3"}, {"chord_ID": "47", "chord_HTML": "IV<sup>7</sup>", "probability": 1, "child_path": "642,164,5,47"}, {"chord_ID": "2", "chord_HTML": "ii", "probability": 0.5, "child_path": "56,4,57,2"}, {"chord_ID": "1", "chord_HTML": "I", "probability": 1, "child_path": "5/5,4,D4,1"}, {"chord_ID": "17", "chord_HTML": "I<sup>7</sup>", "probability": 0.059, "child_path": "27,17,47,17"}, {"chord_ID": "2", "chord_HTML": "ii", "probability": 1, "child_path": "5/6,46,36,2"}, {"chord_ID": "5", "chord_HTML": "V", "probability": 1, "child_path": "2,264,4,5"}, {"chord_ID": "26", "chord_HTML": "ii<sup>6</sup>", "probability": 0.25, "child_path": "2,16,47,26"}, {"chord_ID": "364", "chord_HTML": "iii<sup>6</sup><sub>4</sub>", "probability": 0.051, "child_path": "56,6,1,364"}, {"chord_ID": "5", "chord_HTML": "V", "probability": 1, "child_path": "1,17,46,5"}, {"chord_ID": "27", "chord_HTML": "ii<sup>7</sup>", "probability": 0.5, "child_path": "67,17,47,27"}, {"chord_ID": "6", "chord_HTML": "vi", "probability": 0.5, "child_path": "242,264,242,6"}, {"chord_ID": "M5", "chord_HTML": "v", "probability": 0.031, "child_path": "1,b7,46,M5"}, {"chord_ID": "67", "chord_HTML": "vi<sup>7</sup>", "probability": 1, "child_path": "77,564/6,6,67"}, {"chord_ID": "M143", "chord_HTML": "I<sup>4</sup><sub>3</sub>", "probability": 1, "child_path": "57,5,b57,M143"}, {"chord_ID": "1", "chord_HTML": "I", "probability": 0.105, "child_path": "1,364,4,1"}, {"chord_ID": "26", "chord_HTML": "ii<sup>6</sup>", "probability": 0.067, "child_path": "b7,1,5/5,26"}, {"chord_ID": "47", "chord_HTML": "IV<sup>7</sup>", "probability": 0.222, "child_path": "67,27,1,47"}, {"chord_ID": "47", "chord_HTML": "IV<sup>7</sup>", "probability": 1, "child_path": "57/6,67,77/5,47"}, {"chord_ID": "464", "chord_HTML": "IV<sup>6</sup><sub>4</sub>", "probability": 1, "child_path": "664,16,4,464"}, {"chord_ID": "164", "chord_HTML": "I<sup>6</sup><sub>4</sub>", "probability": 0.006, "child_path": "6,2,6,164"}, {"chord_ID": "264", "chord_HTML": "ii<sup>6</sup><sub>4</sub>", "probability": 0.111, "child_path": "664,66,664,264"}, {"chord_ID": "b77", "chord_HTML": "&#9837;VIIb7", "probability": 1, "child_path": "37,67,b47,b77"}, {"chord_ID": "5", "chord_HTML": "V", "probability": 0.143, "child_path": "5,1,26,5"}, {"chord_ID": "1", "chord_HTML": "I", "probability": 1, "child_path": "6,2,C2,1"}, {"chord_ID": "2", "chord_HTML": "ii", "probability": 0.176, "child_path": "664,66,6,2"}, {"chord_ID": "67", "chord_HTML": "vi<sup>7</sup>", "probability": 0.006, "child_path": "2,1,2,67"}, {"chord_ID": "56", "chord_HTML": "V<sup>6</sup>", "probability": 0.176, "child_path": "16,26,57,56"}, {"chord_ID": "5/6", "chord_HTML": "V/vi", "probability": 0.1, "child_path": "47,2,47,5/6"}, {"chord_ID": "4", "chord_HTML": "IV", "probability": 0.222, "child_path": "4,27,57/6,4"}, {"chord_ID": "7/2", "chord_HTML": "vii&deg;/ii", "probability": 0.13, "child_path": "16,6,5,7/2"}, {"chord_ID": "4", "chord_HTML": "IV", "probability": 0.075, "child_path": "46,L46,46,4"}, {"chord_ID": "1", "chord_HTML": "I", "probability": 0.263, "child_path": "16,5,56,1"}, {"chord_ID": "6", "chord_HTML": "vi", "probability": 0.625, "child_path": "664,2,5/6,6"}, {"chord_ID": "7/3", "chord_HTML": "vii&deg;/iii", "probability": 0.081, "child_path": "66,564/6,6,7/3"}, {"chord_ID": "56", "chord_HTML": "V<sup>6</sup>", "probability": 1, "child_path": "37,265,57/5,56"}, {"chord_ID": "164", "chord_HTML": "I<sup>6</sup><sub>4</sub>", "probability": 0.012, "child_path": "6,1,4,164"}, {"chord_ID": "5/6", "chord_HTML": "V/vi", "probability": 1, "child_path": "4,77,4,5/6"}, {"chord_ID": "5/6", "chord_HTML": "V/vi", "probability": 1, "child_path": "b6,b3,2,5/6"}, {"chord_ID": "164", "chord_HTML": "I<sup>6</sup><sub>4</sub>", "probability": 0.07, "child_path": "6,164,5,164"}, {"chord_ID": "6", "chord_HTML": "vi", "probability": 0.625, "child_path": "1,564/6,5/6,6"}, {"chord_ID": "57/2", "chord_HTML": "V<sup>7</sup>/ii", "probability": 0.5, "child_path": "3,57/6,6,57/2"}, {"chord_ID": "L26", "chord_HTML": "II<sup>6</sup>", "probability": 0.5, "child_path": "4,542,5,L26"}, {"chord_ID": "37", "chord_HTML": "iii<sup>7</sup>", "probability": 0.273, "child_path": "37,5,4,37"}, {"chord_ID": "164", "chord_HTML": "I<sup>6</sup><sub>4</sub>", "probability": 0.001, "child_path": "5,6,5,164"}, {"chord_ID": "5", "chord_HTML": "V", "probability": 0.396, "child_path": "1,5,1,5"}, {"chord_ID": "164", "chord_HTML": "I<sup>6</sup><sub>4</sub>", "probability": 0.005, "child_path": "5,2,6,164"}, {"chord_ID": "56", "chord_HTML": "V<sup>6</sup>", "probability": 0.009, "child_path": "1,4,16,56"}, {"chord_ID": "664", "chord_HTML": "vi<sup>6</sup><sub>4</sub>", "probability": 0.333, "child_path": "5,5/6,27,664"}, {"chord_ID": "7/7", "chord_HTML": "vii&deg;/vii", "probability": 0.667, "child_path": "7,7/7,7,7/7"}, {"chord_ID": "3", "chord_HTML": "iii", "probability": 0.6, "child_path": "6,3,57/2,3"}, {"chord_ID": "565/5", "chord_HTML": "V<sup>6</sup><sub>5</sub>/V", "probability": 0.085, "child_path": "46,b46,164,565/5"}, {"chord_ID": "5/7", "chord_HTML": "V/vii", "probability": 0.1, "child_path": "b3,4,b7,5/7"}, {"chord_ID": "57", "chord_HTML": "V<sup>7</sup>", "probability": 1, "child_path": "542,37,1,57"}, {"chord_ID": "6", "chord_HTML": "vi", "probability": 0.167, "child_path": "5,56,5,6"}, {"chord_ID": "57/6", "chord_HTML": "V<sup>7</sup>/vi", "probability": 0.002, "child_path": "5/6,6,4,57/6"}, {"chord_ID": "46", "chord_HTML": "IV<sup>6</sup>", "probability": 0.016, "child_path": "4,5/6,6,46"}, {"chord_ID": "37", "chord_HTML": "iii<sup>7</sup>", "probability": 0.07, "child_path": "47,57/6,67,37"}, {"chord_ID": "6", "chord_HTML": "vi", "probability": 1, "child_path": "57/5,5,57/6,6"}, {"chord_ID": "464", "chord_HTML": "IV<sup>6</sup><sub>4</sub>", "probability": 0.5, "child_path": "56,164,56,464"}, {"chord_ID": "6", "chord_HTML": "vi", "probability": 0.171, "child_path": "6,4,5/5,6"}, {"chord_ID": "5", "chord_HTML": "V", "probability": 1, "child_path": "5/2,5,47,5"}, {"chord_ID": "2", "chord_HTML": "ii", "probability": 0.083, "child_path": "6,2,27,2"}, {"chord_ID": "5/6", "chord_HTML": "V/vi", "probability": 0.667, "child_path": "4,5/6,5/5,5/6"}, {"chord_ID": "5", "chord_HTML": "V", "probability": 1, "child_path": "46,1,47,5"}, {"chord_ID": "27", "chord_HTML": "ii<sup>7</sup>", "probability": 0.184, "child_path": "16,27,57,27"}, {"chord_ID": "665", "chord_HTML": "vi<sup>6</sup><sub>5</sub>", "probability": 0.231, "child_path": "265,16,2,665"}, {"chord_ID": "6", "chord_HTML": "vi", "probability": 1, "child_path": "665,16,4,6"}, {"chord_ID": "265", "chord_HTML": "ii<sup>6</sup><sub>5</sub>", "probability": 0.002, "child_path": "4,1,6,265"}, {"chord_ID": "6", "chord_HTML": "vi", "probability": 0.071, "child_path": "16,27,5,6"}, {"chord_ID": "4", "chord_HTML": "IV", "probability": 1, "child_path": "6,164,5/5,4"}, {"chord_ID": "4", "chord_HTML": "IV", "probability": 0.375, "child_path": "5,67,17,4"}, {"chord_ID": "77/5", "chord_HTML": "vii<sup>??</sup><sup>7</sup>/V", "probability": 0.346, "child_path": "57/5,57,17,77/5"}, {"chord_ID": "4", "chord_HTML": "IV", "probability": 1, "child_path": "5/5,36,6,4"}, {"chord_ID": "5/7", "chord_HTML": "V/vii", "probability": 0.001, "child_path": "1,5,4,5/7"}, {"chord_ID": "57/6", "chord_HTML": "V<sup>7</sup>/vi", "probability": 0.012, "child_path": "6,4,2,57/6"}, {"chord_ID": "16", "chord_HTML": "I<sup>6</sup>", "probability": 0.25, "child_path": "5,1,564,16"}, {"chord_ID": "56/6", "chord_HTML": "V<sup>6</sup>/vi", "probability": 0.143, "child_path": "1,46,b7,56/6"}, {"chord_ID": "6", "chord_HTML": "vi", "probability": 1, "child_path": "1,5/5,57/6,6"}, {"chord_ID": "642", "chord_HTML": "vi<sup>4</sup><sub>2</sub>", "probability": 1, "child_path": "642,6,664,642"}, {"chord_ID": "5/2", "chord_HTML": "V/ii", "probability": 0.032, "child_path": "5,1,5/6,5/2"}, {"chord_ID": "6", "chord_HTML": "vi", "probability": 1, "child_path": "1,47,57/6,6"}, {"chord_ID": "6", "chord_HTML": "vi", "probability": 0.07, "child_path": "b3,4,5,6"}, {"chord_ID": "L4", "chord_HTML": "&#9839;iv&deg;", "probability": 0.111, "child_path": "2,664,4,L4"}, {"chord_ID": "5", "chord_HTML": "V", "probability": 1, "child_path": "36,4,164,5"}, {"chord_ID": "67", "chord_HTML": "vi<sup>7</sup>", "probability": 0.176, "child_path": "1,142,M142,67"}, {"chord_ID": "5", "chord_HTML": "V", "probability": 0.121, "child_path": "1,57,4,5"}, {"chord_ID": "47", "chord_HTML": "IV<sup>7</sup>", "probability": 0.125, "child_path": "47,2,5,47"}, {"chord_ID": "564", "chord_HTML": "V<sup>6</sup><sub>4</sub>", "probability": 1, "child_path": "5,664,464/5,564"}, {"chord_ID": "5", "chord_HTML": "V", "probability": 1, "child_path": "2,b7,b5,5"}, {"chord_ID": "b6", "chord_HTML": "&#9837;VI", "probability": 0.048, "child_path": "46,4,5,b6"}, {"chord_ID": "26", "chord_HTML": "ii<sup>6</sup>", "probability": 1, "child_path": "6,L7,3,26"}, {"chord_ID": "66", "chord_HTML": "vi<sup>6</sup>", "probability": 0.4, "child_path": "164,C164,6,66"}, {"chord_ID": "6", "chord_HTML": "vi", "probability": 0.043, "child_path": "67,1,4,6"}, {"chord_ID": "47", "chord_HTML": "IV<sup>7</sup>", "probability": 0.353, "child_path": "365,37,67,47"}, {"chord_ID": "5", "chord_HTML": "V", "probability": 1, "child_path": "5,57,56,5"}, {"chord_ID": "27", "chord_HTML": "ii<sup>7</sup>", "probability": 1, "child_path": "6,164,643,27"}, {"chord_ID": "1", "chord_HTML": "I", "probability": 0.132, "child_path": "2,3,6,1"}, {"chord_ID": "543/5", "chord_HTML": "V<sup>4</sup><sub>3</sub>/V", "probability": 0.071, "child_path": "4,1,57/5,543/5"}, {"chord_ID": "365", "chord_HTML": "iii<sup>6</sup><sub>5</sub>", "probability": 0.25, "child_path": "67,47,3,365"}, {"chord_ID": "642", "chord_HTML": "vi<sup>4</sup><sub>2</sub>", "probability": 0.5, "child_path": "66,76/6,6,642"}, {"chord_ID": "27", "chord_HTML": "ii<sup>7</sup>", "probability": 0.25, "child_path": "2,16,6,27"}, {"chord_ID": "4", "chord_HTML": "IV", "probability": 0.259, "child_path": "4,1,37,4"}, {"chord_ID": "37", "chord_HTML": "iii<sup>7</sup>", "probability": 0.5, "child_path": "2,564,6,37"}, {"chord_ID": "5/6", "chord_HTML": "V/vi", "probability": 0.286, "child_path": "3,4,664,5/6"}, {"chord_ID": "6", "chord_HTML": "vi", "probability": 1, "child_path": "5,7/6,76/6,6"}, {"chord_ID": "16", "chord_HTML": "I<sup>6</sup>", "probability": 0.357, "child_path": "67,1,2,16"}, {"chord_ID": "C27", "chord_HTML": "&#9837;II<sup>7</sup>", "probability": 1, "child_path": "57/5,4,b165,C27"}, {"chord_ID": "4", "chord_HTML": "IV", "probability": 0.318, "child_path": "264,5,1,4"}, {"chord_ID": "3", "chord_HTML": "iii", "probability": 0.111, "child_path": "57,1,17,3"}, {"chord_ID": "57/4", "chord_HTML": "V<sup>7</sup>/IV", "probability": 0.188, "child_path": "164,6,56,57/4"}, {"chord_ID": "6", "chord_HTML": "vi", "probability": 0.4, "child_path": "2,6,5/3,6"}, {"chord_ID": "464", "chord_HTML": "IV<sup>6</sup><sub>4</sub>", "probability": 1, "child_path": "4,365,26,464"}, {"chord_ID": "5", "chord_HTML": "V", "probability": 1, "child_path": "264,27,47,5"}, {"chord_ID": "664", "chord_HTML": "vi<sup>6</sup><sub>4</sub>", "probability": 0.1, "child_path": "66,6,4,664"}, {"chord_ID": "5", "chord_HTML": "V", "probability": 0.214, "child_path": "16,27,4,5"}, {"chord_ID": "1", "chord_HTML": "I", "probability": 0.261, "child_path": "5,4,6,1"}, {"chord_ID": "4", "chord_HTML": "IV", "probability": 1, "child_path": "264,1,5,4"}, {"chord_ID": "57", "chord_HTML": "V<sup>7</sup>", "probability": 0.004, "child_path": "6,5,1,57"}, {"chord_ID": "542", "chord_HTML": "V<sup>4</sup><sub>2</sub>", "probability": 1, "child_path": "56,1,565/5,542"}, {"chord_ID": "7/5", "chord_HTML": "vii&deg;/V", "probability": 0.007, "child_path": "6,16,4,7/5"}, {"chord_ID": "7/2", "chord_HTML": "vii&deg;/ii", "probability": 0.5, "child_path": "7/6,264,1,7/2"}, {"chord_ID": "6", "chord_HTML": "vi", "probability": 0.192, "child_path": "3,1,3,6"}, {"chord_ID": "6", "chord_HTML": "vi", "probability": 0.5, "child_path": "6,66,D47,6"}, {"chord_ID": "Y2", "chord_HTML": "&#9837;II", "probability": 1, "child_path": "b7,4,Y3,Y2"}, {"chord_ID": "565/6", "chord_HTML": "V<sup>6</sup><sub>5</sub>/vi", "probability": 0.025, "child_path": "57,1,6,565/6"}, {"chord_ID": "4", "chord_HTML": "IV", "probability": 0.103, "child_path": "564,4,5,4"}, {"chord_ID": "265", "chord_HTML": "ii<sup>6</sup><sub>5</sub>", "probability": 0.026, "child_path": "4,1,5/5,265"}, {"chord_ID": "3", "chord_HTML": "iii", "probability": 0.016, "child_path": "664,4,1,3"}, {"chord_ID": "5", "chord_HTML": "V", "probability": 0.667, "child_path": "265,5,57,5"}, {"chord_ID": "6", "chord_HTML": "vi", "probability": 1, "child_path": "5,37,565/6,6"}, {"chord_ID": "b442", "chord_HTML": "iv<sup>4</sup><sub>2</sub>", "probability": 0.2, "child_path": "4,37,b3,b442"}, {"chord_ID": "1", "chord_HTML": "I", "probability": 1, "child_path": "56,2,16,1"}, {"chord_ID": "47", "chord_HTML": "IV<sup>7</sup>", "probability": 0.011, "child_path": "5,6,56,47"}, {"chord_ID": "1", "chord_HTML": "I", "probability": 0.125, "child_path": "4,36,5,1"}, {"chord_ID": "27", "chord_HTML": "ii<sup>7</sup>", "probability": 0.146, "child_path": "164,1,5,27"}, {"chord_ID": "2", "chord_HTML": "ii", "probability": 0.033, "child_path": "6,b7,4,2"}, {"chord_ID": "47", "chord_HTML": "IV<sup>7</sup>", "probability": 0.003, "child_path": "3,6,4,47"}, {"chord_ID": "642", "chord_HTML": "vi<sup>4</sup><sub>2</sub>", "probability": 0.4, "child_path": "365,17,67,642"}, {"chord_ID": "26", "chord_HTML": "ii<sup>6</sup>", "probability": 0.006, "child_path": "6,3,5,26"}, {"chord_ID": "67", "chord_HTML": "vi<sup>7</sup>", "probability": 0.007, "child_path": "47,5,6,67"}, {"chord_ID": "Y3", "chord_HTML": "&#9837;III", "probability": 0.194, "child_path": "4,6,5/6,Y3"}, {"chord_ID": "D3", "chord_HTML": "&#9837;III", "probability": 0.1, "child_path": "6,642,2,D3"}, {"chord_ID": "56/6", "chord_HTML": "V<sup>6</sup>/vi", "probability": 0.054, "child_path": "2,57/6,6,56/6"}, {"chord_ID": "5/6", "chord_HTML": "V/vi", "probability": 1, "child_path": "5/6,2,7/3,5/6"}, {"chord_ID": "M17", "chord_HTML": "Ib7", "probability": 0.188, "child_path": "57,Y57,57,M17"}, {"chord_ID": "664", "chord_HTML": "vi<sup>6</sup><sub>4</sub>", "probability": 0.001, "child_path": "4,1,5,664"}, {"chord_ID": "57/6", "chord_HTML": "V<sup>7</sup>/vi", "probability": 0.022, "child_path": "4,1,5/6,57/6"}, {"chord_ID": "143", "chord_HTML": "I<sup>4</sup><sub>3</sub>", "probability": 1, "child_path": "464,27,664,143"}, {"chord_ID": "6", "chord_HTML": "vi", "probability": 1, "child_path": "1,6,543/6,6"}, {"chord_ID": "46/6", "chord_HTML": "IV<sup>6</sup>/vi", "probability": 1, "child_path": "664,16,5/5,46/6"}, {"chord_ID": "5", "chord_HTML": "V", "probability": 1, "child_path": "b3,1,67,5"}, {"chord_ID": "164", "chord_HTML": "I<sup>6</sup><sub>4</sub>", "probability": 0.24, "child_path": "27,5/6,6,164"}, {"chord_ID": "47/4", "chord_HTML": "IV<sup>7</sup>/IV", "probability": 0.007, "child_path": "3,4,3,47/4"}, {"chord_ID": "4", "chord_HTML": "IV", "probability": 0.552, "child_path": "1,5,37,4"}, {"chord_ID": "57/5", "chord_HTML": "V<sup>7</sup>/V", "probability": 1, "child_path": "1,164,543/5,57/5"}, {"chord_ID": "4", "chord_HTML": "IV", "probability": 0.333, "child_path": "1,464,564,4"}, {"chord_ID": "46", "chord_HTML": "IV<sup>6</sup>", "probability": 0.036, "child_path": "4,16,564,46"}, {"chord_ID": "27", "chord_HTML": "ii<sup>7</sup>", "probability": 0.039, "child_path": "5,1,6,27"}, {"chord_ID": "Y3", "chord_HTML": "&#9837;III", "probability": 0.019, "child_path": "b7,4,5,Y3"}, {"chord_ID": "2", "chord_HTML": "ii", "probability": 0.25, "child_path": "6,4,57/6,2"}, {"chord_ID": "164", "chord_HTML": "I<sup>6</sup><sub>4</sub>", "probability": 0.003, "child_path": "4,6,5,164"}, {"chord_ID": "b4", "chord_HTML": "iv", "probability": 0.2, "child_path": "6,5,7/5,b4"}, {"chord_ID": "2", "chord_HTML": "ii", "probability": 0.071, "child_path": "564,2,1,2"}, {"chord_ID": "L564", "chord_HTML": "V<sup>6</sup><sub>4</sub>", "probability": 0.143, "child_path": "5,1,26,L564"}, {"chord_ID": "46", "chord_HTML": "IV<sup>6</sup>", "probability": 0.092, "child_path": "1,56,5,46"}, {"chord_ID": "27", "chord_HTML": "ii<sup>7</sup>", "probability": 1, "child_path": "665,L264,67,27"}, {"chord_ID": "243", "chord_HTML": "ii<sup>4</sup><sub>3</sub>", "probability": 0, "child_path": "6,4,5,243"}, {"chord_ID": "5/5", "chord_HTML": "V/V", "probability": 0.145, "child_path": "3,5/5,1,5/5"}, {"chord_ID": "5", "chord_HTML": "V", "probability": 0.25, "child_path": "16,C16,27,5"}, {"chord_ID": "4", "chord_HTML": "IV", "probability": 1, "child_path": "37,5,2,4"}, {"chord_ID": "7/2", "chord_HTML": "vii&deg;/ii", "probability": 1, "child_path": "2,b5,7/4,7/2"}, {"chord_ID": "1", "chord_HTML": "I", "probability": 1, "child_path": "564,464,4,1"}, {"chord_ID": "1", "chord_HTML": "I", "probability": 1, "child_path": "5,5/2,2,1"}, {"chord_ID": "5/2", "chord_HTML": "V/ii", "probability": 0.049, "child_path": "2,1,b7,5/2"}, {"chord_ID": "164", "chord_HTML": "I<sup>6</sup><sub>4</sub>", "probability": 1, "child_path": "164,464,242,164"}, {"chord_ID": "27", "chord_HTML": "ii<sup>7</sup>", "probability": 0.231, "child_path": "27,57,67,27"}, {"chord_ID": "443", "chord_HTML": "IV<sup>4</sup><sub>3</sub>", "probability": 0.133, "child_path": "2,3,47,443"}, {"chord_ID": "5", "chord_HTML": "V", "probability": 1, "child_path": "57,2,b76,5"}, {"chord_ID": "1", "chord_HTML": "I", "probability": 0.5, "child_path": "57,5/7,57,1"}, {"chord_ID": "142", "chord_HTML": "I<sup>4</sup><sub>2</sub>", "probability": 1, "child_path": "57,b6,57,142"}, {"chord_ID": "6", "chord_HTML": "vi", "probability": 1, "child_path": "36,265,57/6,6"}, {"chord_ID": "3", "chord_HTML": "iii", "probability": 0.1, "child_path": "16,6,2,3"}, {"chord_ID": "4", "chord_HTML": "IV", "probability": 0.75, "child_path": "664,2,3,4"}, {"chord_ID": "164", "chord_HTML": "I<sup>6</sup><sub>4</sub>", "probability": 0.333, "child_path": "57/2,2,4,164"}, {"chord_ID": "3", "chord_HTML": "iii", "probability": 0.75, "child_path": "36,47,2,3"}, {"chord_ID": "442", "chord_HTML": "IV<sup>4</sup><sub>2</sub>", "probability": 0.028, "child_path": "57,1,4,442"}, {"chord_ID": "5", "chord_HTML": "V", "probability": 1, "child_path": "4,67,6,5"}, {"chord_ID": "664", "chord_HTML": "vi<sup>6</sup><sub>4</sub>", "probability": 0.01, "child_path": "2,6,2,664"}, {"chord_ID": "57", "chord_HTML": "V<sup>7</sup>", "probability": 0.061, "child_path": "1,164,5,57"}, {"chord_ID": "4", "chord_HTML": "IV", "probability": 1, "child_path": "4,5,5/7,4"}, {"chord_ID": "36", "chord_HTML": "iii<sup>6</sup>", "probability": 0.625, "child_path": "37,M67,27,36"}, {"chord_ID": "27", "chord_HTML": "ii<sup>7</sup>", "probability": 0.008, "child_path": "2,5,6,27"}, {"chord_ID": "4", "chord_HTML": "IV", "probability": 0.217, "child_path": "164,67,16,4"}, {"chord_ID": "6", "chord_HTML": "vi", "probability": 0.081, "child_path": "17,27,37,6"}, {"chord_ID": "6", "chord_HTML": "vi", "probability": 0.794, "child_path": "4,5,7/6,6"}, {"chord_ID": "47", "chord_HTML": "IV<sup>7</sup>", "probability": 0.5, "child_path": "67,142,17,47"}, {"chord_ID": "57", "chord_HTML": "V<sup>7</sup>", "probability": 0.125, "child_path": "57/6,67,57/5,57"}, {"chord_ID": "4", "chord_HTML": "IV", "probability": 0.5, "child_path": "564,5,3,4"}, {"chord_ID": "47", "chord_HTML": "IV<sup>7</sup>", "probability": 0.083, "child_path": "77,57/6,6,47"}, {"chord_ID": "47", "chord_HTML": "IV<sup>7</sup>", "probability": 1, "child_path": "46,b5,1,47"}, {"chord_ID": "56", "chord_HTML": "V<sup>6</sup>", "probability": 0.045, "child_path": "1,464,1,56"}, {"chord_ID": "3", "chord_HTML": "iii", "probability": 0.034, "child_path": "2,4,6,3"}, {"chord_ID": "6", "chord_HTML": "vi", "probability": 0.084, "child_path": "4,1,4,6"}, {"chord_ID": "16", "chord_HTML": "I<sup>6</sup>", "probability": 0.429, "child_path": "16,3,4,16"}, {"chord_ID": "56/6", "chord_HTML": "V<sup>6</sup>/vi", "probability": 0.5, "child_path": "26,16,2,56/6"}, {"chord_ID": "5/2", "chord_HTML": "V/ii", "probability": 0.001, "child_path": "6,5,4,5/2"}, {"chord_ID": "664", "chord_HTML": "vi<sup>6</sup><sub>4</sub>", "probability": 0.462, "child_path": "47,365,27,664"}, {"chord_ID": "164", "chord_HTML": "I<sup>6</sup><sub>4</sub>", "probability": 1, "child_path": "57,46,17,164"}, {"chord_ID": "46", "chord_HTML": "IV<sup>6</sup>", "probability": 1, "child_path": "365,4,464,46"}, {"chord_ID": "5", "chord_HTML": "V", "probability": 1, "child_path": "4,5/5,57/5,5"}, {"chord_ID": "2", "chord_HTML": "ii", "probability": 0.122, "child_path": "5,57/6,6,2"}, {"chord_ID": "1", "chord_HTML": "I", "probability": 1, "child_path": "67,27,b4,1"}, {"chord_ID": "b4", "chord_HTML": "iv", "probability": 0.019, "child_path": "56,1,4,b4"}, {"chord_ID": "6", "chord_HTML": "vi", "probability": 0.8, "child_path": "4,5/5,36,6"}, {"chord_ID": "264", "chord_HTML": "ii<sup>6</sup><sub>4</sub>", "probability": 0.6, "child_path": "5/2,564/2,27,264"}, {"chord_ID": "6", "chord_HTML": "vi", "probability": 0.75, "child_path": "6,5,642,6"}, {"chord_ID": "1", "chord_HTML": "I", "probability": 0.828, "child_path": "265,1,265,1"}, {"chord_ID": "1", "chord_HTML": "I", "probability": 0.25, "child_path": "6,564,5,1"}, {"chord_ID": "5", "chord_HTML": "V", "probability": 1, "child_path": "564,2,47,5"}, {"chord_ID": "6", "chord_HTML": "vi", "probability": 0.333, "child_path": "2,26,2,6"}, {"chord_ID": "5/6", "chord_HTML": "V/vi", "probability": 1, "child_path": "5/6,2,D3,5/6"}, {"chord_ID": "3", "chord_HTML": "iii", "probability": 0.032, "child_path": "27,37,4,3"}, {"chord_ID": "564", "chord_HTML": "V<sup>6</sup><sub>4</sub>", "probability": 0.073, "child_path": "1,46,56,564"}, {"chord_ID": "56/6", "chord_HTML": "V<sup>6</sup>/vi", "probability": 0.033, "child_path": "7,5/6,6,56/6"}, {"chord_ID": "5", "chord_HTML": "V", "probability": 0.105, "child_path": "56,2,4,5"}, {"chord_ID": "4", "chord_HTML": "IV", "probability": 1, "child_path": "564,5,27,4"}, {"chord_ID": "57", "chord_HTML": "V<sup>7</sup>", "probability": 0.25, "child_path": "57,D47,1,57"}, {"chord_ID": "5", "chord_HTML": "V", "probability": 0.75, "child_path": "37,6,3,5"}, {"chord_ID": "364", "chord_HTML": "iii<sup>6</sup><sub>4</sub>", "probability": 0.031, "child_path": "4,57,1,364"}, {"chord_ID": "27", "chord_HTML": "ii<sup>7</sup>", "probability": 1, "child_path": "27,5,M77,27"}, {"chord_ID": "6", "chord_HTML": "vi", "probability": 1, "child_path": "56,47,36,6"}, {"chord_ID": "47", "chord_HTML": "IV<sup>7</sup>", "probability": 0.143, "child_path": "57/6,6,642,47"}, {"chord_ID": "1", "chord_HTML": "I", "probability": 1, "child_path": "36,3,4,1"}, {"chord_ID": "47", "chord_HTML": "IV<sup>7</sup>", "probability": 0.52, "child_path": "365,47,365,47"}, {"chord_ID": "26", "chord_HTML": "ii<sup>6</sup>", "probability": 0.01, "child_path": "1,5,4,26"}, {"chord_ID": "1", "chord_HTML": "I", "probability": 0.5, "child_path": "1,5,243,1"}, {"chord_ID": "26", "chord_HTML": "ii<sup>6</sup>", "probability": 0.333, "child_path": "16,6,642,26"}, {"chord_ID": "57", "chord_HTML": "V<sup>7</sup>", "probability": 0.25, "child_path": "57/5,1,5,57"}, {"chord_ID": "5", "chord_HTML": "V", "probability": 0.333, "child_path": "6,26,164,5"}, {"chord_ID": "1", "chord_HTML": "I", "probability": 1, "child_path": "b3,5,3,1"}, {"chord_ID": "57/5", "chord_HTML": "V<sup>7</sup>/V", "probability": 0.016, "child_path": "5,7/6,6,57/5"}, {"chord_ID": "27", "chord_HTML": "ii<sup>7</sup>", "probability": 0.025, "child_path": "1,4,5/6,27"}, {"chord_ID": "56/5", "chord_HTML": "V<sup>6</sup>/V", "probability": 1, "child_path": "3,364,4,56/5"}, {"chord_ID": "2", "chord_HTML": "ii", "probability": 0.273, "child_path": "1,47,37,2"}, {"chord_ID": "1", "chord_HTML": "I", "probability": 0.058, "child_path": "57,1,56,1"}, {"chord_ID": "3", "chord_HTML": "iii", "probability": 0.021, "child_path": "2,57,1,3"}, {"chord_ID": "3", "chord_HTML": "iii", "probability": 0.235, "child_path": "1,7,5,3"}, {"chord_ID": "4", "chord_HTML": "IV", "probability": 1, "child_path": "7/6,6,164,4"}, {"chord_ID": "4", "chord_HTML": "IV", "probability": 0.333, "child_path": "57,1,17,4"}, {"chord_ID": "5", "chord_HTML": "V", "probability": 1, "child_path": "2,6,665,5"}, {"chord_ID": "265", "chord_HTML": "ii<sup>6</sup><sub>5</sub>", "probability": 0.214, "child_path": "6,665,2,265"}, {"chord_ID": "642", "chord_HTML": "vi<sup>4</sup><sub>2</sub>", "probability": 0.006, "child_path": "1,6,1,642"}, {"chord_ID": "5", "chord_HTML": "V", "probability": 0.357, "child_path": "4,664,4,5"}, {"chord_ID": "7", "chord_HTML": "vii&deg;", "probability": 0.055, "child_path": "4,3,1,7"}, {"chord_ID": "5", "chord_HTML": "V", "probability": 1, "child_path": "2,16,265,5"}, {"chord_ID": "6", "chord_HTML": "vi", "probability": 0.769, "child_path": "4,27,3,6"}, {"chord_ID": "2", "chord_HTML": "ii", "probability": 0.714, "child_path": "3,4,664,2"}, {"chord_ID": "47", "chord_HTML": "IV<sup>7</sup>", "probability": 0.026, "child_path": "6,56/6,6,47"}]